wch/__init__.py
wch/change_detector.py
wch/watcher.py
wch/wch.py
wch-0.4.0.dist-info/entry_points.txt
wch-0.4.0.dist-info/LICENSE
wch-0.4.0.dist-info/WHEEL
wch-0.4.0.dist-info/METADATA
wch-0.4.0.dist-info/RECORD
